sparsity/__init__.py
sparsity/_version.py
sparsity/indexing.py
sparsity/io.py
sparsity/sparse_frame.py
sparsity/dask/__init__.py
sparsity/dask/core.py
sparsity/dask/indexing.py
sparsity/dask/io.py
sparsity/dask/multi.py
sparsity/dask/reshape.py
sparsity/dask/shuffle.py
sparsity-0.19.1.dist-info/METADATA
sparsity-0.19.1.dist-info/RECORD
sparsity-0.19.1.dist-info/WHEEL
sparsity-0.19.1.dist-info/top_level.txt
