Metadata-Version: 2.1
Name: sparsity
Version: 0.19.1
Summary: Sparse data processing toolbox
Home-page: https://github.com/datarevenue-berlin/sparsity
Author: Alan Hoeng
Author-email: alan.f.hoeng@gmail.com
License: UNKNOWN
Platform: UNKNOWN
Classifier: Programming Language :: Python :: 3
Classifier: License :: OSI Approved :: BSD License
Classifier: Operating System :: OS Independent
Requires-Dist: pandas (<=0.23.4,>=0.19.0)
Requires-Dist: scipy (>=0.18.1)
Requires-Dist: numpy (>=1.12.0)
Requires-Dist: s3fs (>=0.1.0)
